snakemake_storage_plugin_latch/__init__.py
snakemake_storage_plugin_latch-0.1.11.dist-info/METADATA
snakemake_storage_plugin_latch-0.1.11.dist-info/WHEEL
snakemake_storage_plugin_latch-0.1.11.dist-info/RECORD
