Metadata-Version: 2.1
Name: snakemake-storage-plugin-latch
Version: 0.1.11
Summary: 
Author: Ayush Kamat
Author-email: ayush@latch.bio
Requires-Python: >=3.11
Classifier: Programming Language :: Python :: 3
Classifier: Programming Language :: Python :: 3.11
Classifier: Programming Language :: Python :: 3.12
Requires-Dist: gql (>=3.5.0,<4.0.0)
Requires-Dist: latch-persistence (==0.1.5)
Requires-Dist: python-dateutil (>=2.9.0.post0,<3.0.0)
Requires-Dist: requests-toolbelt (>=1.0.0,<2.0.0)
Requires-Dist: snakemake-interface-storage-plugins (>=3.3.0,<4.0.0)
